Metadata-Version: 1.0
Name: giseed
Version: 1.4.0
Summary: Tool developed for GI course on ETF Belgrade
Home-page: https://github.com/accchi/GI-project
Author: Marko Aleksandar Marko
Author-email: UNKNOWN
License: MIT
Keywords: bwt,genomics,seed&extend
Platform: UNKNOWN
